automata/__init__.py
automata/automata.py
automata/utils/__init__.py
automata/utils/errors.py
automata/utils/payloads.py
automata_ws-0.1.1.dist-info/LICENSE
automata_ws-0.1.1.dist-info/METADATA
automata_ws-0.1.1.dist-info/WHEEL
automata_ws-0.1.1.dist-info/top_level.txt
automata_ws-0.1.1.dist-info/RECORD
