Metadata-Version: 2.1
Name: automata-ws
Version: 0.1.1
Summary: Automata is a lightweight framework that allows users to define a state machine based websocket server.
Author: Erik Lungulescu
License: Apache License, Version 2.0
Project-URL: Source, https://github.com/eriklungulescu/Automata
Keywords: automata,websocket,server,state machine,event
Classifier: Development Status :: 4 - Beta
Classifier: Programming Language :: Python :: 3
Classifier: Framework :: AsyncIO
Classifier: Intended Audience :: Developers
Classifier: License :: OSI Approved :: Apache Software License
Requires-Python: >=3.7
License-File: LICENSE
Requires-Dist: websockets (>=10.4)
